Metadata-Version: 2.1
Name: Mquotes2
Version: 1.0.0
Summary: A library for displaying money related quotes
Author: Phani Kumar
Author-email: x21175098@student.ncirl.ie
Classifier: Development Status :: 4 - Beta
Classifier: Intended Audience :: Developers
Classifier: License :: OSI Approved :: MIT License
Classifier: Programming Language :: Python :: 3
Classifier: Programming Language :: Python :: 3.6
Classifier: Programming Language :: Python :: 3.7
Classifier: Programming Language :: Python :: 3.8
Classifier: Programming Language :: Python :: 3.9
